kasabuttons/__init__.py
kasabuttons/buttons.py
kasabuttons/configuration.py
kasabuttons/core.py
kasabuttons/kasa_cli.py
kasabuttons/kasa_utils.py
kasabuttons/logging_utils.py
kasabuttons/keyboard_handlers/__init__.py
kasabuttons/keyboard_handlers/base_handler.py
kasabuttons/keyboard_handlers/keyboard_handler.py
kasabuttons/keyboard_handlers/pynput_handler.py
kasabuttons-0.3.2.dist-info/METADATA
kasabuttons-0.3.2.dist-info/WHEEL
kasabuttons-0.3.2.dist-info/entry_points.txt
kasabuttons-0.3.2.dist-info/licenses/LICENSE
kasabuttons-0.3.2.dist-info/RECORD
