Metadata-Version: 2.3
Name: kasabuttons
Version: 0.3.2
Summary: Add your description here
Author-email: swilcox <steven@wilcoxzone.com>
Requires-Python: >=3.11
Requires-Dist: click>=8.1.7
Requires-Dist: keyboard>=0.13.5
Requires-Dist: loguru-config>=0.1.0
Requires-Dist: loguru>=0.7.2
Requires-Dist: loki-logger-handler>=0.1.4
Requires-Dist: pydantic-settings>=2.2.1
Requires-Dist: pynput>=1.7.7
Requires-Dist: python-dotenv>=1.0.1
Requires-Dist: python-kasa>=0.7.6
Requires-Dist: pyyaml>=6.0.1
Requires-Dist: requests>=2.32.3
